azure/mgmt/storage/__init__.py
azure/mgmt/storage/_configuration.py
azure/mgmt/storage/_serialization.py
azure/mgmt/storage/_storage_management_client.py
azure/mgmt/storage/_version.py
azure/mgmt/storage/models.py
azure/mgmt/storage/py.typed
azure/mgmt/storage/aio/__init__.py
azure/mgmt/storage/aio/_configuration.py
azure/mgmt/storage/aio/_storage_management_client.py
azure/mgmt/storage/v2016_01_01/__init__.py
azure/mgmt/storage/v2016_01_01/_configuration.py
azure/mgmt/storage/v2016_01_01/_patch.py
azure/mgmt/storage/v2016_01_01/_storage_management_client.py
azure/mgmt/storage/v2016_01_01/_version.py
azure/mgmt/storage/v2016_01_01/py.typed
azure/mgmt/storage/v2016_01_01/aio/__init__.py
azure/mgmt/storage/v2016_01_01/aio/_configuration.py
azure/mgmt/storage/v2016_01_01/aio/_patch.py
azure/mgmt/storage/v2016_01_01/aio/_storage_management_client.py
azure/mgmt/storage/v2016_01_01/aio/operations/__init__.py
azure/mgmt/storage/v2016_01_01/aio/operations/_patch.py
azure/mgmt/storage/v2016_01_01/aio/operations/_storage_accounts_operations.py
azure/mgmt/storage/v2016_01_01/aio/operations/_usage_operations.py
azure/mgmt/storage/v2016_01_01/models/__init__.py
azure/mgmt/storage/v2016_01_01/models/_models_py3.py
azure/mgmt/storage/v2016_01_01/models/_patch.py
azure/mgmt/storage/v2016_01_01/models/_storage_management_client_enums.py
azure/mgmt/storage/v2016_01_01/operations/__init__.py
azure/mgmt/storage/v2016_01_01/operations/_patch.py
azure/mgmt/storage/v2016_01_01/operations/_storage_accounts_operations.py
azure/mgmt/storage/v2016_01_01/operations/_usage_operations.py
azure/mgmt/storage/v2017_10_01/__init__.py
azure/mgmt/storage/v2017_10_01/_configuration.py
azure/mgmt/storage/v2017_10_01/_patch.py
azure/mgmt/storage/v2017_10_01/_storage_management.py
azure/mgmt/storage/v2017_10_01/_version.py
azure/mgmt/storage/v2017_10_01/py.typed
azure/mgmt/storage/v2017_10_01/aio/__init__.py
azure/mgmt/storage/v2017_10_01/aio/_configuration.py
azure/mgmt/storage/v2017_10_01/aio/_patch.py
azure_mgmt_storage-22.2.0.dist-info/LICENSE
azure_mgmt_storage-22.2.0.dist-info/METADATA
azure_mgmt_storage-22.2.0.dist-info/WHEEL
azure_mgmt_storage-22.2.0.dist-info/top_level.txt
azure_mgmt_storage-22.2.0.dist-info/RECORD
